libvivp/__init__.py
libvivp/utils.py
libvivp/vPackage.py
vivp-0.0.6.data/scripts/vivp
vivp-0.0.6.dist-info/LICENSE.txt
vivp-0.0.6.dist-info/METADATA
vivp-0.0.6.dist-info/WHEEL
vivp-0.0.6.dist-info/top_level.txt
vivp-0.0.6.dist-info/RECORD
