Metadata-Version: 2.1
Name: vivp
Version: 0.0.6
Summary: A package manager for Verilog Projects
Home-page: https://github.com/AdityaNG/VIVP
Author: Aditya NG
Author-email: adityang5@gmail.com
License: LICENSE.txt
Platform: UNKNOWN
Requires-Python: >=3.6
